<?xml version="1.0" encoding="UTF-8" standalone="yes"?>
<codeset>
    <label>Birth Order</label>
    <type>BIRTH_ORDER</type>
    <code>
        <value>5</value>
        <label>Fifth</label>
        <description></description>
        <code-status>
            <status>Valid</status>
        </code-status>
    </code>
    <code>
        <value>1</value>
        <label>First</label>
        <description></description>
        <code-status>
            <status>Valid</status>
        </code-status>
    </code>
    <code>
        <value>4</value>
        <label>Fourth</label>
        <description></description>
        <code-status>
            <status>Valid</status>
        </code-status>
    </code>
    <code>
        <value>2</value>
        <label>Second</label>
        <description></description>
        <code-status>
            <status>Valid</status>
        </code-status>
    </code>
    <code>
        <value>3</value>
        <label>Third</label>
        <description></description>
        <code-status>
            <status>Valid</status>
        </code-status>
    </code>
</codeset>
